Metadata-Version: 1.1
Name: webfinger
Version: 1.0
Summary: Simple Python implementation of WebFinger client protocol
Home-page: http://github.com/jcarbaugh/python-webfinger/
Author: Jeremy Carbaugh
Author-email: jcarbaugh@gmail.com
License: BSD
Platform: any
Classifier: Development Status :: 5 - Production/Stable
Classifier: Intended Audience :: Developers
Classifier: License :: OSI Approved :: BSD License
Classifier: Natural Language :: English
Classifier: Operating System :: OS Independent
Classifier: Programming Language :: Python
Classifier: Topic :: Software Development :: Libraries :: Python Modules
